[
  {
    "job": "Supino",
    "selected": false,
    "series": "3x12"
  },
  {
    "job": "Supino",
    "selected": false,
    "series": "3x12"
  },
  {
    "job": "Supino",
    "selected": false,
    "series": "3x12"
  },
  {
    "job": "Supino",
    "selected": false,
    "series": "3x12"
  },
  {
    "job": "Supino",
    "selected": false,
    "series": "3x12"
  },
  {
    "job": "Supino",
    "selected": false,
    "series": "3x12"
  },
  {
    "job": "Supino",
    "selected": false,
    "series": "3x12"
  },
  {
    "job": "Supino",
    "selected": false,
    "series": "3x12"
  },
  {
    "job": "Supino",
    "selected": false,
    "series": "3x12"
  }
]
